sandbox_cli/__main__.py
sandbox_cli/console.py
sandbox_cli/cli/__init__.py
sandbox_cli/cli/downloader.py
sandbox_cli/cli/images.py
sandbox_cli/cli/reporter.py
sandbox_cli/cli/unpack.py
sandbox_cli/cli/rules/__init__.py
sandbox_cli/cli/scanner/__init__.py
sandbox_cli/internal/__init__.py
sandbox_cli/internal/config.py
sandbox_cli/internal/helpers.py
sandbox_cli/models/__init__.py
sandbox_cli/models/detections.py
sandbox_cli/models/sandbox_arguments.py
sandbox_cli/utils/__init__.py
sandbox_cli/utils/extractors.py
sandbox_cli/utils/merge_dll_hooks.py
sandbox_cli/utils/compiler/__init__.py
sandbox_cli/utils/compiler/abc.py
sandbox_cli/utils/compiler/docker.py
sandbox_cli/utils/compiler/ssh.py
sandbox_cli/utils/downloader/__init__.py
sandbox_cli/utils/scanner/__init__.py
sandbox_cli/utils/scanner/advanced.py
sandbox_cli/utils/scanner/rescan.py
sandbox_cli/utils/unpack/__init__.py
sandbox_cli/utils/unpack/plugins/__init__.py
sandbox_cli/utils/unpack/plugins/abc.py
sandbox_cli/utils/unpack/plugins/correlation.py
sandbox_cli/utils/unpack/plugins/sort_by_plugins.py
sandbox_cli-0.2.45.dist-info/METADATA
sandbox_cli-0.2.45.dist-info/WHEEL
sandbox_cli-0.2.45.dist-info/entry_points.txt
sandbox_cli-0.2.45.dist-info/licenses/LICENSE
sandbox_cli-0.2.45.dist-info/licenses/NOTICE
sandbox_cli-0.2.45.dist-info/RECORD
