Metadata-Version: 2.4
Name: sandbox-cli
Version: 0.2.45
Summary: Command line tool for interaction with sandboxes
Project-URL: Homepage, https://github.com/Security-Experts-Community/sandbox-cli
Project-URL: Documentation, https://security-experts-community.github.io/sandbox-cli
Project-URL: Repository, https://github.com/Security-Experts-Community/sandbox-cli
Project-URL: Issues, https://github.com/Security-Experts-Community/sandbox-cli/issues
Author: Alexey Kolesnikov
License-Expression: MIT
License-File: LICENSE
License-File: NOTICE
Requires-Python: >=3.11
Requires-Dist: aiofiles>=24.1.0
Requires-Dist: asyncssh>=2.21.1
Requires-Dist: colorama>=0.4.6
Requires-Dist: cryptography>=46.0.2
Requires-Dist: cyclopts>=4.2.5
Requires-Dist: docker>=7.1.0
Requires-Dist: ptsandbox>=5.0.8
Requires-Dist: pyzipper>=0.3.6
Requires-Dist: rich>=14.1.0
Requires-Dist: zstandard>=0.23.0
